agentarium/Agent.py
agentarium/AgentInteractionManager.py
agentarium/CheckpointManager.py
agentarium/Config.py
agentarium/Environment.py
agentarium/Interaction.py
agentarium/__init__.py
agentarium/constant.py
agentarium/utils.py
agentarium/actions/Action.py
agentarium/actions/default_actions.py
agentarium-0.3.1.dist-info/METADATA
agentarium-0.3.1.dist-info/WHEEL
agentarium-0.3.1.dist-info/licenses/LICENSE
agentarium-0.3.1.dist-info/RECORD
