Metadata-Version: 2.4
Name: agentarium
Version: 0.3.1
Summary: A framework for managing and orchestrating AI agents
Project-URL: Homepage, https://github.com/thytu/Agentarium
Author: thytu
License-File: LICENSE
Classifier: License :: OSI Approved :: Apache Software License
Classifier: Operating System :: OS Independent
Classifier: Programming Language :: Python :: 3
Requires-Python: >=3.10
Requires-Dist: aisuite>=0.1.7
Requires-Dist: boto3>=1.35.86
Requires-Dist: dill>=0.3.8
Requires-Dist: faker>=33.1.0
Requires-Dist: openai>=1.57.2
Requires-Dist: pyyaml>=6.0.1
Provides-Extra: test
Requires-Dist: pytest-cov>=4.0.0; extra == 'test'
Requires-Dist: pytest>=7.0.0; extra == 'test'
